{
  "goods": [
    {
      "id": 10001,
      "title":"三星 ssd（SAMSUNG）500GB SSD固态硬盘 SATA3.0接口 870 EVO（MZ-77E500B）",
      "label":["固态硬盘","三星"],
      "category":"数码",
      "price": 489,
      "stock":50
    },
    {
      "id": 10002,
      "title":"AMD 锐龙7 cpu 5800X 处理器7nm 8核16线程 3.8GHz AM4接口 盒装CPU",
      "label":["锐龙","CPU"],
      "category":"数码",
      "price": 3099,
      "stock":30
    },
    {
      "id": 10003,
      "title":"蒙牛 特仑苏 纯牛奶 年货必备 250ml*16 礼盒装",
      "label":["纯牛奶","蒙牛"],
      "category":"超市",
      "price": 80,
      "stock":30
    },
    {
      "id": 10004,
      "title":"西域美农 开心果250g/袋 饱满颗粒 每日坚果炒货 孕妇儿童休闲零食小吃",
      "label":["开心果","坚果"],
      "category":"超市",
      "price": 30,
      "stock":30
    },
    {
      "id": 10005,
      "title":"合生元（BIOSTIME）派星 幼儿配方奶粉 3段(12-36个月) 法国原装原罐进口 900克",
      "label":["奶粉","合生元"],
      "category":"奶粉",
      "price": 310,
      "stock":30
    },
    {
      "id": 10006,
      "title":"飞鹤星飞帆 婴儿配方奶粉 1段(0-6个月婴儿适用) 300克",
      "label":["婴儿配方奶粉","飞鹤"],
      "category":"奶粉",
      "price": 129,
      "stock":30
    },
    {
      "id": 10007,
      "title":"J-VAN春季夹克男士外套秋冬季加绒加厚工装休闲衣服套装棉羊羔绒男装冬装牛仔潮流卫衣连帽秋季短款风衣 3件",
      "label":["夹克","衣服"],
      "category":"服装",
      "price": 199,
      "stock":30
    },
    {
      "id": 10008,
      "title":"报喜鸟男装商务休闲立领棉服 青年男士修身薄款外套 ESS194010U111 深绿 52",
      "label":["棉服","报喜鸟"],
      "category":"服装",
      "price": 960,
      "stock":30
    }
  ],
  "hot":[
    {
      "id": 20001,
      "title":"京东云无线宝路由器 2100M双频双千兆 家用穿墙 信号放大 赚积分兑京豆 坐享其成",
      "label":["路由器","京东云"],
      "category":"数码",
      "price": 209,
      "oPrice": 229,
      "stock":30
    },
    {
      "id": 20002,
      "title":"三全 炫彩小汤圆 四合一组合装 260g 52只（黑芝麻/花生/紫薯/抹茶）早餐 点心 甜品",
      "label":["汤圆","三全"],
      "category":"超市",
      "price": 16.9,
      "oPrice": 25,
      "stock":30
    }
  ],

}